emhass/__init__.py
emhass/command_line.py
emhass/connection_manager.py
emhass/forecast.py
emhass/machine_learning_forecaster.py
emhass/machine_learning_regressor.py
emhass/optimization.py
emhass/retrieve_hass.py
emhass/utils.py
emhass/web_server.py
emhass/websocket_client.py
emhass/data/associations.csv
emhass/data/cec_inverters.pbz2
emhass/data/cec_modules.pbz2
emhass/data/config_defaults.json
emhass/img/emhass_icon.png
emhass/static/advanced.html
emhass/static/basic.html
emhass/static/configuration_list.html
emhass/static/configuration_script.js
emhass/static/script.js
emhass/static/style.css
emhass/static/data/param_definitions.json
emhass/static/img/emhass_icon.png
emhass/static/img/emhass_logo_short.svg
emhass/static/img/feather-sprite.svg
emhass/templates/configuration.html
emhass/templates/index.html
emhass/templates/template.html
emhass-0.16.2.dist-info/METADATA
emhass-0.16.2.dist-info/WHEEL
emhass-0.16.2.dist-info/entry_points.txt
emhass-0.16.2.dist-info/licenses/LICENSE
emhass-0.16.2.dist-info/RECORD
