Metadata-Version: 2.4
Name: emhass
Version: 0.16.2
Summary: An Energy Management System for Home Assistant
Project-URL: Homepage, https://github.com/davidusb-geek/emhass
Project-URL: Source, https://github.com/davidusb-geek/emhass
Project-URL: Issues, https://github.com/davidusb-geek/emhass/issues
Project-URL: Documentation, https://emhass.readthedocs.io/en/latest/
Project-URL: Community, https://community.home-assistant.io/t/emhass-an-energy-management-for-home-assistant
Author-email: David HERNANDEZ TORRES <davidusb@gmail.com>
License: MIT
License-File: LICENSE
Keywords: energy,hass,management,optimization
Classifier: Development Status :: 5 - Production/Stable
Classifier: Intended Audience :: Developers
Classifier: License :: OSI Approved :: MIT License
Classifier: Operating System :: OS Independent
Classifier: Programming Language :: Python :: 3 :: Only
Classifier: Programming Language :: Python :: 3.10
Classifier: Programming Language :: Python :: 3.11
Classifier: Programming Language :: Python :: 3.12
Classifier: Topic :: Software Development :: Libraries :: Python Modules
Requires-Python: <3.13,>=3.10
Requires-Dist: aiofiles
Requires-Dist: aiohttp
Requires-Dist: asyncio
Requires-Dist: cvxpy>=1.6.0
Requires-Dist: gunicorn>=23.0.0
Requires-Dist: h5py>=3.12.1
Requires-Dist: highspy>=1.10.0
Requires-Dist: influxdb>=5.3.1
Requires-Dist: jinja2
Requires-Dist: numpy<2.3.0,>=2.0.0
Requires-Dist: orjson
Requires-Dist: pandas>=2.2.0
Requires-Dist: plotly>=6.0.0
Requires-Dist: protobuf>=5.29.3
Requires-Dist: pvlib>=0.11.0
Requires-Dist: pytz>=2024.2
Requires-Dist: pyyaml>=6.0.2
Requires-Dist: quart
Requires-Dist: scipy>=1.15.0
Requires-Dist: skforecast<0.20.0,>=0.19.1
Requires-Dist: tables>=3.10.0
Requires-Dist: uvicorn==0.30.6
Requires-Dist: waitress>=3.0.2
Requires-Dist: websockets
Provides-Extra: dev
Requires-Dist: ruff; extra == 'dev'
Provides-Extra: docs
Requires-Dist: myst-parser; extra == 'docs'
Requires-Dist: pydata-sphinx-theme; extra == 'docs'
Requires-Dist: sphinx; extra == 'docs'
Requires-Dist: sphinx-design; extra == 'docs'
Provides-Extra: test
Requires-Dist: aioresponses; extra == 'test'
Requires-Dist: coverage; extra == 'test'
Requires-Dist: hatchling; extra == 'test'
Requires-Dist: pytest; extra == 'test'
Requires-Dist: pytz; extra == 'test'
Requires-Dist: ruff; extra == 'test'
Requires-Dist: snakeviz; extra == 'test'
Requires-Dist: tabulate; extra == 'test'
